OpenShockPY/__init__.py
OpenShockPY/async_client.py
OpenShockPY/cli.py
OpenShockPY/client.py
OpenShockPY/py.typed
nanashi_openshockpy-0.0.1.5.dist-info/licenses/LICENSE.md
nanashi_openshockpy-0.0.1.5.dist-info/METADATA
nanashi_openshockpy-0.0.1.5.dist-info/WHEEL
nanashi_openshockpy-0.0.1.5.dist-info/top_level.txt
nanashi_openshockpy-0.0.1.5.dist-info/RECORD
