Metadata-Version: 2.4
Name: Nanashi-OpenShockPY
Version: 0.0.1.5
Summary: UNOFFICIAL Lightweight Python client for the OpenShock API
Author: NanashiTheNameless
Author-email: NanashiTheNameless <NanashiTheNameless@NamelessNanashi.dev>
Maintainer: NanashiTheNameless
Maintainer-email: NanashiTheNameless <NanashiTheNameless@NamelessNanashi.dev>
License: NNCL v1.3-MODIFIED-OpenShockPY
Project-URL: Homepage, https://github.com/NanashiTheNameless/OpenShockPY
Project-URL: Issues, https://github.com/NanashiTheNameless/OpenShockPY/issues
Project-URL: GitHub Sponsor, https://github.com/sponsors/NanashiTheNameless
Project-URL: Buy Me a Coffee, https://buymeacoffee.com/NamelessNanashi
Classifier: Development Status :: 3 - Alpha
Classifier: Intended Audience :: Developers
Classifier: Natural Language :: English
Classifier: License :: Other/Proprietary License
Classifier: Programming Language :: Python :: 3
Classifier: Programming Language :: Python :: 3.8
Classifier: Programming Language :: Python :: 3.9
Classifier: Programming Language :: Python :: 3.10
Classifier: Programming Language :: Python :: 3.11
Classifier: Programming Language :: Python :: 3.12
Classifier: Programming Language :: Python :: 3.13
Classifier: Operating System :: OS Independent
Classifier: Topic :: Software Development :: Libraries :: Python Modules
Classifier: Topic :: Internet :: WWW/HTTP :: Dynamic Content
Classifier: Typing :: Typed
Requires-Python: >=3.8
License-File: LICENSE.md
Requires-Dist: requests>=2.32.0
Provides-Extra: cli
Requires-Dist: keyring>=25.7.0; extra == "cli"
Provides-Extra: dev
Requires-Dist: pytest>=9.0.2; extra == "dev"
Requires-Dist: pytest-asyncio>=1.3.0; extra == "dev"
Requires-Dist: respx>=0.20.0; extra == "dev"
Requires-Dist: httpx>=0.24.0; extra == "dev"
Provides-Extra: async
Requires-Dist: httpx>=0.24.0; extra == "async"
Requires-Dist: pytest-asyncio>=1.3.0; extra == "async"
Requires-Dist: respx>=0.20.0; extra == "async"
Provides-Extra: all
Requires-Dist: keyring>=25.7.0; extra == "all"
Requires-Dist: pytest>=9.0.2; extra == "all"
Requires-Dist: httpx>=0.24.0; extra == "all"
Requires-Dist: pytest-asyncio>=1.3.0; extra == "all"
Requires-Dist: respx>=0.20.0; extra == "all"
Dynamic: license-file
